accountr/__init__.py
accountr/accounting_utils.py
accountr/app.py
accountr/constants.py
accountr/database.py
accountr/database_management_ui.py
accountr/database_switcher.py
accountr/excel_export.py
accountr/excel_utils.py
accountr/helpers.py
accountr/main.py
accountr/translation_utils.py
accountr/translations.py
accountr/pages/__init__.py
accountr/pages/account_balances_page.py
accountr/pages/balance_sheet_page.py
accountr/pages/base_page.py
accountr/pages/chart_of_accounts_page.py
accountr/pages/file_management_page.py
accountr/pages/journal_entries_page.py
accountr/pages/result_sheet_page.py
accountr/pages/stock_management_page.py
accountr/pages/year_closing_page.py
accountr-0.1.0.dist-info/licenses/LICENSE
accountr-0.1.0.dist-info/METADATA
accountr-0.1.0.dist-info/WHEEL
accountr-0.1.0.dist-info/entry_points.txt
accountr-0.1.0.dist-info/top_level.txt
accountr-0.1.0.dist-info/RECORD
