Metadata-Version: 2.4
Name: accountr
Version: 0.1.0
Summary: A simple accounting application built with Python, Streamlit, and SQLAlchemy
Author-email: Nicolas Jacquemin <n.jacquemin1993@gmail.com>
License: MIT License
Project-URL: Homepage, https://github.com/njacquemin1993/accounting
Project-URL: Bug Tracker, https://github.com/njacquemin1993/accounting/issues
Project-URL: Repository, https://github.com/njacquemin1993/accounting
Keywords: accounting,bookkeeping,streamlit,finance
Classifier: Development Status :: 4 - Beta
Classifier: Intended Audience :: End Users/Desktop
Classifier: License :: OSI Approved :: MIT License
Classifier: Operating System :: OS Independent
Classifier: Programming Language :: Python :: 3
Classifier: Programming Language :: Python :: 3.12
Classifier: Topic :: Office/Business :: Financial :: Accounting
Requires-Python: >=3.12
License-File: LICENSE
Requires-Dist: streamlit>=1.52.0
Requires-Dist: sqlalchemy>=2.0.23
Requires-Dist: pandas>=2.1.4
Requires-Dist: plotly>=5.17.0
Requires-Dist: xlsxwriter>=3.1.9
Provides-Extra: dev
Requires-Dist: pytest>=7.0; extra == "dev"
Requires-Dist: ruff>=0.14.8; extra == "dev"
Requires-Dist: mypy>=1.0; extra == "dev"
Dynamic: license-file
